sqlitely/__init__.py
sqlitely/__main__.py
sqlitely/components.py
sqlitely/conf.py
sqlitely/database.py
sqlitely/gui.py
sqlitely/guibase.py
sqlitely/images.py
sqlitely/importexport.py
sqlitely/main.py
sqlitely/plugins.py
sqlitely/scheme.py
sqlitely/searchparser.py
sqlitely/support.py
sqlitely/templates.py
sqlitely/workers.py
sqlitely/bin/sqlite3_analyzer.exe
sqlitely/bin/sqlite3_analyzer_linux
sqlitely/bin/sqlite3_analyzer_linux_x64
sqlitely/bin/sqlite3_analyzer_osx
sqlitely/etc/sqlitely.ini
sqlitely/grammar/SQLite.g4
sqlitely/grammar/SQLiteLexer.py
sqlitely/grammar/SQLiteParser.py
sqlitely/grammar/__init__.py
sqlitely/grammar/sqlite.py
sqlitely/grammar/templates.py
sqlitely/lib/__init__.py
sqlitely/lib/controls.py
sqlitely/lib/util.py
sqlitely/lib/wx_accel.py
sqlitely/media/Carlito.ttf
sqlitely/media/CarlitoBold.ttf
sqlitely/media/OpenSans.ttf
sqlitely/media/OpenSansBold.ttf
sqlitely-2.4.dist-info/LICENSE.md
sqlitely-2.4.dist-info/METADATA
sqlitely-2.4.dist-info/WHEEL
sqlitely-2.4.dist-info/entry_points.txt
sqlitely-2.4.dist-info/top_level.txt
sqlitely-2.4.dist-info/RECORD
