Metadata-Version: 2.1
Name: sqlitely
Version: 2.4
Summary: SQLite database tool
Home-page: https://github.com/suurjaak/SQLitely
Author: Erki Suurjaak
Author-email: erki@lap.ee
License: MIT
Keywords: sqlite database
Platform: any
Classifier: Development Status :: 5 - Production/Stable
Classifier: Intended Audience :: End Users/Desktop
Classifier: Operating System :: Microsoft :: Windows
Classifier: Operating System :: Unix
Classifier: Operating System :: MacOS
Classifier: Topic :: Database
Classifier: Topic :: Utilities
Classifier: Topic :: Desktop Environment
Classifier: License :: OSI Approved :: MIT License
Classifier: Programming Language :: Python :: 2
Classifier: Programming Language :: Python :: 2.7
Classifier: Programming Language :: Python :: 3
License-File: LICENSE.md
Requires-Dist: appdirs
Requires-Dist: chardet
Requires-Dist: openpyxl
Requires-Dist: Pillow
Requires-Dist: pyparsing
Requires-Dist: pytz
Requires-Dist: pyyaml
Requires-Dist: six
Requires-Dist: step-template (>=0.0.4)
Requires-Dist: wxPython (>=4.0)
Requires-Dist: xlrd
Requires-Dist: XlsxWriter
Requires-Dist: antlr4-python2-runtime (==4.13.0) ; python_version < "3"
Requires-Dist: antlr4-python3-runtime (==4.13.0) ; python_version > "3"
Provides-Extra: tests
Requires-Dist: xlwt ; extra == 'tests'
